{
  "_class": "shapeGroup",
  "clippingMaskMode": 0,
  "do_objectID": "43DAB5B2-71BA-4F99-A80C-650603AAE67B",
  "exportOptions": {
    "_class": "exportOptions",
    "exportFormats": [
    ],
    "includedLayerIds": [
    ],
    "layerOptions": 0,
    "shouldTrim": false
  },
  "frame": {
    "_class": "rect",
    "constrainProportions": false,
    "height": 48,
    "width": 90,
    "x": 0,
    "y": 0
  },
  "hasClickThrough": false,
  "hasClippingMask": false,
  "isFlippedHorizontal": false,
  "isFlippedVertical": false,
  "isLocked": false,
  "isVisible": true,
  "layerListExpandedType": 0,
  "layers": [
    {
      "class": "rectangle",
      "id": "13362F9A-9292-4B9B-8002-28E5E0674D5A"
    }
  ],
  "name": "BG",
  "nameIsFixed": true,
  "resizingConstraint": 63,
  "resizingType": 0,
  "rotation": 0,
  "shouldBreakMaskChain": false,
  "style": {
    "_class": "style",
    "do_objectID": "383382DA-9E91-49F9-AF0D-E9A61FD31F3E",
    "endDecorationType": 0,
    "fills": [
      {
        "_class": "fill",
        "color": {
          "_class": "color",
          "alpha": 0,
          "blue": 1,
          "green": 1,
          "red": 1
        },
        "fillType": 0,
        "isEnabled": true,
        "noiseIndex": 0,
        "noiseIntensity": 0,
        "patternFillType": 1,
        "patternTileScale": 1
      }
    ],
    "miterLimit": 10,
    "shadows": [
      {
        "_class": "shadow",
        "blurRadius": 0,
        "color": {
          "_class": "color",
          "alpha": 1,
          "blue": 0.9327434098639455,
          "green": 0.9243706539554841,
          "red": 0.9243706539554841
        },
        "contextSettings": {
          "_class": "graphicsContextSettings",
          "blendMode": 0,
          "opacity": 1
        },
        "isEnabled": true,
        "offsetX": 0,
        "offsetY": 1,
        "spread": 0
      }
    ],
    "sharedObjectID": "8181686C-A25F-4AFF-A0BE-9E2FCBD2847B",
    "startDecorationType": 0
  },
  "userInfo": {
    "com.animaapp.stc-sketch-plugin": {
      "kModelPropertiesKey": {
      }
    }
  },
  "windingRule": 1
}