{
  "_class": "shapeGroup",
  "clippingMaskMode": 0,
  "do_objectID": "2AEAE0FB-95F8-441D-B201-BBA6EC3EEA4F",
  "exportOptions": {
    "_class": "exportOptions",
    "exportFormats": [
    ],
    "includedLayerIds": [
    ],
    "layerOptions": 0,
    "shouldTrim": false
  },
  "frame": {
    "_class": "rect",
    "constrainProportions": false,
    "height": 40,
    "width": 196,
    "x": 0,
    "y": 0
  },
  "hasClickThrough": false,
  "hasClippingMask": false,
  "isFlippedHorizontal": false,
  "isFlippedVertical": false,
  "isLocked": false,
  "isVisible": true,
  "layerListExpandedType": 0,
  "layers": [
    {
      "class": "rectangle",
      "id": "80CBBEF5-53E3-478B-9BAA-51F90A74C945"
    }
  ],
  "name": "Border",
  "nameIsFixed": true,
  "resizingConstraint": 63,
  "resizingType": 0,
  "rotation": 0,
  "shouldBreakMaskChain": false,
  "style": {
    "sharedObjectID": "90401C50-BB78-4743-B91F-FFB026030363"
  },
  "windingRule": 1
}